flask_jsonschema.py
Flask_JsonSchema_All-0.1.1.dist-info/LICENSE
Flask_JsonSchema_All-0.1.1.dist-info/METADATA
Flask_JsonSchema_All-0.1.1.dist-info/WHEEL
Flask_JsonSchema_All-0.1.1.dist-info/top_level.txt
Flask_JsonSchema_All-0.1.1.dist-info/RECORD
